shellerator/__init__.py
shellerator/data/shells.json
shellerator/requirements.txt
shellerator/shellerator.py
shellerator-900.0.1.dist-info/WHEEL
shellerator-900.0.1.dist-info/entry_points.txt
shellerator-900.0.1.dist-info/METADATA
shellerator-900.0.1.dist-info/RECORD
