Metadata-Version: 2.3
Name: shellerator
Version: 900.0.1
Summary: A simple CLI tool to generate reverse, bind and web shells
Requires-Dist: argparse>=1.4.0
Requires-Dist: colorama>=0.4.6
Requires-Dist: console-menu>=0.8.0
Requires-Dist: psutil>=7.2.1
Requires-Dist: simple-term-menu>=1.6.6
Requires-Python: >=3.7
